calc/__init__.py
calc2003-0.1.dist-info/LICENSE.txt
calc2003-0.1.dist-info/METADATA
calc2003-0.1.dist-info/WHEEL
calc2003-0.1.dist-info/top_level.txt
calc2003-0.1.dist-info/RECORD
