Metadata-Version: 2.1
Name: calc2003
Version: 0.1
Summary: calculator used only for addition
Author: vkr
Author-email: rakalyanram@gmail.com
Classifier: Programming Language :: Python :: 3
Classifier: License :: OSI Approved :: MIT License
Classifier: Operating System :: OS Independent
License-File: LICENSE.txt
